lanex/tests/goldens/sim_run/counter.v
module counter(input clk, input rst, output reg [3:0] q);
  always @(posedge clk) begin
    if (rst) q <= 4'd0;
    else     q <= q + 4'd1;
  end
endmodule

lanex/tests/goldens/sim_run/tb_counter.v
`timescale 1ns/1ns
module tb_counter;
  reg clk = 1'b0;
  reg rst = 1'b1;
  wire [3:0] q;
  counter dut(.clk(clk), .rst(rst), .q(q));
  always #5 clk = ~clk;
  initial begin
    $dumpfile("dump.vcd");
    $dumpvars(0, tb_counter);
    #12 rst = 1'b0;
    #88 $finish;
  end
endmodule

lanex/tests/goldens/sim_run/dump.vcd
$date
	Mon Jul 13 03:06:16 2026
$end
$version
	Icarus Verilog
$end
$timescale
	1ns
$end
$scope module tb_counter $end
$var wire 4 ! q [3:0] $end
$var reg 1 " clk $end
$var reg 1 # rst $end
$scope module dut $end
$var wire 1 " clk $end
$var wire 1 # rst $end
$var reg 4 $ q [3:0] $end
$upscope $end
$upscope $end
$enddefinitions $end
$comment Show the parameter values. $end
$dumpall
$end
#0
$dumpvars
bx $
1#
0"
bx !
$end
#5
b0 !
b0 $
1"
#10
0"
#12
0#
#15
b1 !
b1 $
1"
#20
0"
#25
b10 !
b10 $
1"
#30
0"
#35
b11 !
b11 $
1"
#40
0"
#45
b100 !
b100 $
1"
#50
0"
#55
b101 !
b101 $
1"
#60
0"
#65
b110 !
b110 $
1"
#70
0"
#75
b111 !
b111 $
1"
#80
0"
#85
b1000 !
b1000 $
1"
#90
0"
#95
b1001 !
b1001 $
1"
